snf_simple/__init__.py
snf_simple-0.1.1.dist-info/LICENSE
snf_simple-0.1.1.dist-info/WHEEL
snf_simple-0.1.1.dist-info/METADATA
snf_simple-0.1.1.dist-info/RECORD
