Metadata-Version: 2.1
Name: snf-simple
Version: 0.1.1
Summary: Similarity Network Fusion (SNF) python implementation
Home-page: https://github.com/fmakdemir/snf
License: LGPL-3.0-or-later
Author: fmakdemir
Author-email: fmakdemir@users.noreply.github.com
Requires-Python: >=3.6,<4.0
Classifier: License :: OSI Approved :: GNU Lesser General Public License v3 or later (LGPLv3+)
Classifier: Programming Language :: Python :: 3
Classifier: Programming Language :: Python :: 3.6
Classifier: Programming Language :: Python :: 3.7
Classifier: Programming Language :: Python :: 3.8
Requires-Dist: numpy (>=1.19.1,<2.0.0)
Requires-Dist: scikit-learn (>=0.23.2,<0.24.0)
Project-URL: Repository, https://github.com/fmakdemir/snf
